iocparser/__init__.py
iocparser/iocparser.py
iocparser-1.0.11.data/data/data/extensions
iocparser-1.0.11.data/data/data/tlds
iocparser-1.0.11.dist-info/METADATA
iocparser-1.0.11.dist-info/RECORD
iocparser-1.0.11.dist-info/WHEEL
iocparser-1.0.11.dist-info/top_level.txt
