Metadata-Version: 2.1
Name: iocparser
Version: 1.0.11
Summary: scrapes IOCs from plaintext
Home-page: https://github.com/renzejongman/iocparser
Author: Renze Jongman
Author-email: info@renzejongman.nl
License: UNKNOWN
Platform: UNKNOWN
Classifier: Programming Language :: Python :: 3
Classifier: License :: OSI Approved :: MIT License
Classifier: Operating System :: OS Independent
